spammer_py/__init__.py
spammer_py/spam_disk_ram.py
spammer_py/spam_email.py
spammer_py-0.1.3.dist-info/LICENSE
spammer_py-0.1.3.dist-info/WHEEL
spammer_py-0.1.3.dist-info/METADATA
spammer_py-0.1.3.dist-info/RECORD
